<?xml version="1.0" encoding="ISO-8859-1" standalone="yes"?><env:Envelope xmlns:SOAP-ENC="http://schemas.xmlsoap.org/soap/encoding/" xmlns:env="http://schemas.xmlsoap.org/soap/envelope/" xmlns:xsi="http://www.w3.org/1999/XMLSchema-instance" xmlns:soapenc="http://schemas.xmlsoap.org/soap/encoding/" xmlns:xsd="http://www.w3.org/1999/XMLSchema" env:encodingStyle="http://schemas.xmlsoap.org/soap/encoding/"><env:Header><a:AppContext xmlns:a="http://www.crs.lombardia.it/schemas/mw/2004-01/appcontext/"><Reply servProd="CRM"><Subject>SAVersion 1.3.1_05</Subject></Reply></a:AppContext></env:Header><env:Body><m:CRM.visualizzaListaRefertiResponse xmlns:m="http://www.crs.lombardia.it/schemas/DCSanita/CRM/2008-01/visualizzaListaReferti/"><param><visualizzaListaReferti><datiCittadino><dataNascitaCittadino></dataNascitaCittadino><sessoCittadino></sessoCittadino><comuneNascitaCittadino></comuneNascitaCittadino><idCittadinoNonSISS></idCittadinoNonSISS><idAssistito>171FW588</idAssistito><nomeCittadino>CITT1</nomeCittadino><cognomeCittadino>CITT1</cognomeCittadino><codiceFiscaleCittadino>TSTCRM02T02T002T</codiceFiscaleCittadino></datiCittadino><listaReferti><elemListaReferti><prestazioniAssociate><prestazione><descPrestazione></descPrestazione><idPrescrizione></idPrescrizione><descBrancaSpecialistica></descBrancaSpecialistica><idPrestazione>005</idPrestazione><idEvento>1174</idEvento><idBrancaSpecialistica></idBrancaSpecialistica></prestazione></prestazioniAssociate><datiReferto><livelloOscuramento>00</livelloOscuramento><linkImmagine>link_immagine</linkImmagine><linkDocumentoCDA2>link_doc</linkDocumentoCDA2><reteDiPatologia></reteDiPatologia><noteReperibilita></noteReperibilita><idStruttura>030968</idStruttura><idSubStruttura>03096800</idSubStruttura><numeroNosologico></numeroNosologico><visibilitaCittadino>N</visibilitaCittadino><tipoImmagine>01</tipoImmagine><descrizioneSubStruttura>A.O. "IST.CLIN.PERFEZIONAMENTO"-MILANO</descrizioneSubStruttura><linkRefertoPadre></linkRefertoPadre><tipoReferto>01</tipoReferto><numeroPratica></numeroPratica><naturaReferto>01</naturaReferto><linkReferto>030968.refertoSpecialistico.0001</linkReferto><codiceAggregazioneReferto>74</codiceAggregazioneReferto><descTipoReferto>AMBULATORIO</descTipoReferto><dataReferto>20010910</dataReferto><descNaturaReferto>Standard</descNaturaReferto></datiReferto><datiMedicoRefertante><nomeMedico></nomeMedico><cognomeMedico></cognomeMedico><idStrutturaMedico>030968</idStrutturaMedico><codiceMedico>GVASDR74B12C957V</codiceMedico><ruoloOperatore></ruoloOperatore><descStrutturaMedico>A.O. ISTITUTI CLINICI DI PERFEZIONAMENTO</descStrutturaMedico></datiMedicoRefertante></elemListaReferti><elemListaReferti><prestazioniAssociate><prestazione><descPrestazione></descPrestazione><idPrescrizione></idPrescrizione><descBrancaSpecialistica></descBrancaSpecialistica><idPrestazione>006</idPrestazione><idEvento>1175</idEvento><idBrancaSpecialistica></idBrancaSpecialistica></prestazione></prestazioniAssociate><datiReferto><livelloOscuramento>02</livelloOscuramento><linkImmagine>link_immagine</linkImmagine><linkDocumentoCDA2>link_doc</linkDocumentoCDA2><reteDiPatologia></reteDiPatologia><noteReperibilita></noteReperibilita><idStruttura>030968</idStruttura><idSubStruttura>03096800</idSubStruttura><numeroNosologico></numeroNosologico><visibilitaCittadino>N</visibilitaCittadino><tipoImmagine>01</tipoImmagine><descrizioneSubStruttura>A.O. "IST.CLIN.PERFEZIONAMENTO"-MILANO</descrizioneSubStruttura><linkRefertoPadre></linkRefertoPadre><tipoReferto>01</tipoReferto><numeroPratica></numeroPratica><naturaReferto>01</naturaReferto><linkReferto>030968.refertoSpecialistico.0002</linkReferto><codiceAggregazioneReferto>75</codiceAggregazioneReferto><descTipoReferto>AMBULATORIO</descTipoReferto><dataReferto>20010910</dataReferto><descNaturaReferto>Standard</descNaturaReferto></datiReferto><datiMedicoRefertante><nomeMedico></nomeMedico><cognomeMedico></cognomeMedico><idStrutturaMedico>030968</idStrutturaMedico><codiceMedico>GVASDR74B12C957V</codiceMedico><ruoloOperatore></ruoloOperatore><descStrutturaMedico>A.O. ISTITUTI CLINICI DI PERFEZIONAMENTO</descStrutturaMedico></datiMedicoRefertante></elemListaReferti><elemListaReferti><prestazioniAssociate></prestazioniAssociate><datiReferto><livelloOscuramento>00</livelloOscuramento><linkImmagine>linkAllegato</linkImmagine><linkDocumentoCDA2>uri_dce_cda</linkDocumentoCDA2><reteDiPatologia></reteDiPatologia><noteReperibilita>pippo</noteReperibilita><idStruttura>030968</idStruttura><idUnitaOperativaClinica>100</idUnitaOperativaClinica><idSubStruttura>03096800</idSubStruttura><numeroNosologico></numeroNosologico><visibilitaCittadino>AUTORIZZATO</visibilitaCittadino><tipoImmagine>01</tipoImmagine><descrizioneSubStruttura>A.O. "IST.CLIN.PERFEZIONAMENTO"-MILANO</descrizioneSubStruttura><linkRefertoPadre></linkRefertoPadre><tipoReferto>09</tipoReferto><numeroPratica></numeroPratica><naturaReferto>STD</naturaReferto><linkReferto>uri_dce_txt.1</linkReferto><codiceAggregazioneReferto></codiceAggregazioneReferto><descTipoReferto>PATIENT SUMMARY</descTipoReferto><versioneDCE>1</versioneDCE><dataReferto>20010402</dataReferto><descNaturaReferto>STANDARD</descNaturaReferto></datiReferto><datiMedicoRefertante><nomeMedico>GRAZIANO</nomeMedico><cognomeMedico>ANGELE'</cognomeMedico><idStrutturaMedico></idStrutturaMedico><codiceMedico>GVASDR74B12C957V</codiceMedico><ruoloOperatore>2</ruoloOperatore><descStrutturaMedico></descStrutturaMedico></datiMedicoRefertante></elemListaReferti><elemListaReferti><prestazioniAssociate></prestazioniAssociate><datiReferto><livelloOscuramento>02</livelloOscuramento><linkImmagine>linkAllegato</linkImmagine><linkDocumentoCDA2>uri_dce_cda</linkDocumentoCDA2><reteDiPatologia></reteDiPatologia><noteReperibilita>pippo</noteReperibilita><idStruttura>030968</idStruttura><idUnitaOperativaClinica>100</idUnitaOperativaClinica><idSubStruttura>03096800</idSubStruttura><numeroNosologico></numeroNosologico><visibilitaCittadino>AUTORIZZATO</visibilitaCittadino><tipoImmagine>01</tipoImmagine><descrizioneSubStruttura>A.O. "IST.CLIN.PERFEZIONAMENTO"-MILANO</descrizioneSubStruttura><linkRefertoPadre></linkRefertoPadre><tipoReferto>09</tipoReferto><numeroPratica></numeroPratica><naturaReferto>STD</naturaReferto><linkReferto>uri_dce_txt.2</linkReferto><codiceAggregazioneReferto></codiceAggregazioneReferto><descTipoReferto>PATIENT SUMMARY</descTipoReferto><versioneDCE>1</versioneDCE><dataReferto>20010402</dataReferto><descNaturaReferto>STANDARD</descNaturaReferto></datiReferto><datiMedicoRefertante><nomeMedico>GRAZIANO</nomeMedico><cognomeMedico>ANGELE'</cognomeMedico><idStrutturaMedico></idStrutturaMedico><codiceMedico>GVASDR74B12C957V</codiceMedico><ruoloOperatore>2</ruoloOperatore><descStrutturaMedico></descStrutturaMedico></datiMedicoRefertante></elemListaReferti></listaReferti><datiEsitoServizio><esitoServizio>OK</esitoServizio></datiEsitoServizio><parametriRicerca><reteDiPatologia></reteDiPatologia><idAssistito></idAssistito><tipoReferto></tipoReferto><dataInizio>20010101</dataInizio><dataFine>20011231</dataFine><codiceStrutturaErogatrice></codiceStrutturaErogatrice><idCittadinoNonSISS></idCittadinoNonSISS><codiceFiscaleCittadino>TSTCRM02T02T002T</codiceFiscaleCittadino><codiceMedicoRefertante></codiceMedicoRefertante></parametriRicerca></visualizzaListaReferti></param></m:CRM.visualizzaListaRefertiResponse></env:Body></env:Envelope>